schemdraw_markdown.py
schemdraw_markdown-0.0.3.dist-info/LICENSE
schemdraw_markdown-0.0.3.dist-info/WHEEL
schemdraw_markdown-0.0.3.dist-info/METADATA
schemdraw_markdown-0.0.3.dist-info/RECORD
