Metadata-Version: 2.1
Name: schemdraw-markdown
Version: 0.0.3
Summary: Schemdraw Markdown - A simpler way to document simple circuits in markdown.
Author-email: Joe Stanley <engineerjoe440@yahoo.com>
Classifier: License :: OSI Approved :: MIT License
Requires-Dist: markdown
Requires-Dist: schemdraw[svgmath]
Project-URL: Home, https://github.com/engineerjoe440/schemdraw-markdown
